<stg><name>mlp</name>


<trans_list>

<trans id="83" from="1" to="2">
<condition id="-1">
<or_exp><and_exp></and_exp></or_exp>
</condition>
</trans>

<trans id="84" from="2" to="4">
<condition id="-1">
<or_exp><and_exp><literal name="icmp_ln392" val="1"/>
</and_exp></or_exp>
</condition>
</trans>

<trans id="85" from="2" to="3">
<condition id="-1">
<or_exp><and_exp><literal name="icmp_ln392" val="0"/>
</and_exp></or_exp>
</condition>
</trans>

<trans id="93" from="3" to="2">
<condition id="-1">
<or_exp><and_exp></and_exp></or_exp>
</condition>
</trans>

<trans id="95" from="4" to="5">
<condition id="-1">
<or_exp><and_exp></and_exp></or_exp>
</condition>
</trans>

<trans id="96" from="5" to="6">
<condition id="-1">
<or_exp><and_exp><literal name="icmp_ln401" val="0"/>
</and_exp></or_exp>
</condition>
</trans>

<trans id="98" from="6" to="7">
<condition id="-1">
<or_exp><and_exp></and_exp></or_exp>
</condition>
</trans>

<trans id="99" from="7" to="5">
<condition id="-1">
<or_exp><and_exp></and_exp></or_exp>
</condition>
</trans>
</trans_list>



<state_list>

<state id="1" st_id="1">

<operation id="8" st_id="1" stage="1" lat="1">
<core>NULL</core>
<MemPortIdVec></MemPortIdVec>
<condition id="-1">
<or_exp><and_exp></and_exp></or_exp>
</condition>

<Node id="19" bw="0" op_0_bw="0" op_1_bw="8">
<![CDATA[
:0  call void (...)* @_ssdm_op_SpecBitsMap(i8* %in_V), !map !23

]]></Node>
<StgValue><ssdm name="specbitsmap_ln0"/></StgValue>
</operation>

<operation id="9" st_id="1" stage="1" lat="1">
<core>NULL</core>
<MemPortIdVec></MemPortIdVec>
<condition id="-1">
<or_exp><and_exp></and_exp></or_exp>
</condition>

<Node id="20" bw="0" op_0_bw="0" op_1_bw="16">
<![CDATA[
:1  call void (...)* @_ssdm_op_SpecBitsMap(i16* %out_V), !map !29

]]></Node>
<StgValue><ssdm name="specbitsmap_ln0"/></StgValue>
</operation>

<operation id="10" st_id="1" stage="1" lat="1">
<core>NULL</core>
<MemPortIdVec></MemPortIdVec>
<condition id="-1">
<or_exp><and_exp></and_exp></or_exp>
</condition>

<Node id="21" bw="0" op_0_bw="0" op_1_bw="0">
<![CDATA[
:2  call void (...)* @_ssdm_op_SpecTopModule([4 x i8]* @mlp_str) nounwind

]]></Node>
<StgValue><ssdm name="spectopmodule_ln0"/></StgValue>
</operation>

<operation id="11" st_id="1" stage="1" lat="1">
<core>RAM</core>
<MemPortIdVec></MemPortIdVec>
<condition id="-1">
<or_exp><and_exp></and_exp></or_exp>
</condition>

<Node id="22" bw="8" op_0_bw="64">
<![CDATA[
:3  %sample_0 = alloca [8 x i8], align 1

]]></Node>
<StgValue><ssdm name="sample_0"/><MemPortTyVec>2 3 </MemPortTyVec>
</StgValue>
</operation>

<operation id="12" st_id="1" stage="1" lat="1">
<core>RAM</core>
<MemPortIdVec></MemPortIdVec>
<condition id="-1">
<or_exp><and_exp></and_exp></or_exp>
</condition>

<Node id="23" bw="8" op_0_bw="64">
<![CDATA[
:4  %sample_1 = alloca [8 x i8], align 1

]]></Node>
<StgValue><ssdm name="sample_1"/><MemPortTyVec>2 3 </MemPortTyVec>
</StgValue>
</operation>

<operation id="13" st_id="1" stage="1" lat="1">
<core>RAM</core>
<MemPortIdVec></MemPortIdVec>
<condition id="-1">
<or_exp><and_exp></and_exp></or_exp>
</condition>

<Node id="24" bw="8" op_0_bw="64">
<![CDATA[
:5  %sample_2 = alloca [8 x i8], align 1

]]></Node>
<StgValue><ssdm name="sample_2"/><MemPortTyVec>2 3 </MemPortTyVec>
</StgValue>
</operation>

<operation id="14" st_id="1" stage="1" lat="1">
<core>RAM</core>
<MemPortIdVec></MemPortIdVec>
<condition id="-1">
<or_exp><and_exp></and_exp></or_exp>
</condition>

<Node id="25" bw="8" op_0_bw="64">
<![CDATA[
:6  %sample_3 = alloca [8 x i8], align 1

]]></Node>
<StgValue><ssdm name="sample_3"/><MemPortTyVec>2 3 </MemPortTyVec>
</StgValue>
</operation>

<operation id="15" st_id="1" stage="1" lat="1">
<core>RAM</core>
<MemPortIdVec></MemPortIdVec>
<condition id="-1">
<or_exp><and_exp></and_exp></or_exp>
</condition>

<Node id="26" bw="8" op_0_bw="64">
<![CDATA[
:7  %sample_4 = alloca [8 x i8], align 1

]]></Node>
<StgValue><ssdm name="sample_4"/><MemPortTyVec>2 3 </MemPortTyVec>
</StgValue>
</operation>

<operation id="16" st_id="1" stage="1" lat="1">
<core>RAM</core>
<MemPortIdVec></MemPortIdVec>
<condition id="-1">
<or_exp><and_exp></and_exp></or_exp>
</condition>

<Node id="27" bw="8" op_0_bw="64">
<![CDATA[
:8  %sample_5 = alloca [8 x i8], align 1

]]></Node>
<StgValue><ssdm name="sample_5"/><MemPortTyVec>2 3 </MemPortTyVec>
</StgValue>
</operation>

<operation id="17" st_id="1" stage="1" lat="1">
<core>RAM</core>
<MemPortIdVec></MemPortIdVec>
<condition id="-1">
<or_exp><and_exp></and_exp></or_exp>
</condition>

<Node id="28" bw="8" op_0_bw="64">
<![CDATA[
:9  %sample_6 = alloca [8 x i8], align 1

]]></Node>
<StgValue><ssdm name="sample_6"/><MemPortTyVec>2 3 </MemPortTyVec>
</StgValue>
</operation>

<operation id="18" st_id="1" stage="1" lat="1">
<core>RAM</core>
<MemPortIdVec></MemPortIdVec>
<condition id="-1">
<or_exp><and_exp></and_exp></or_exp>
</condition>

<Node id="29" bw="8" op_0_bw="64">
<![CDATA[
:10  %sample_7 = alloca [8 x i8], align 1

]]></Node>
<StgValue><ssdm name="sample_7"/><MemPortTyVec>2 3 </MemPortTyVec>
</StgValue>
</operation>

<operation id="19" st_id="1" stage="1" lat="1">
<core>RAM</core>
<MemPortIdVec></MemPortIdVec>
<condition id="-1">
<or_exp><and_exp></and_exp></or_exp>
</condition>

<Node id="30" bw="16" op_0_bw="64">
<![CDATA[
:11  %prediction_0 = alloca [5 x i16], align 2

]]></Node>
<StgValue><ssdm name="prediction_0"/><MemPortTyVec>2 3 </MemPortTyVec>
</StgValue>
</operation>

<operation id="20" st_id="1" stage="1" lat="1">
<core>RAM</core>
<MemPortIdVec></MemPortIdVec>
<condition id="-1">
<or_exp><and_exp></and_exp></or_exp>
</condition>

<Node id="31" bw="16" op_0_bw="64">
<![CDATA[
:12  %prediction_1 = alloca [5 x i16], align 2

]]></Node>
<StgValue><ssdm name="prediction_1"/><MemPortTyVec>2 3 </MemPortTyVec>
</StgValue>
</operation>

<operation id="21" st_id="1" stage="1" lat="1">
<core>NULL</core>
<MemPortIdVec></MemPortIdVec>
<condition id="-1">
<or_exp><and_exp></and_exp></or_exp>
</condition>

<Node id="32" bw="0" op_0_bw="0" op_1_bw="8" op_2_bw="0" op_3_bw="32" op_4_bw="32" op_5_bw="0" op_6_bw="32" op_7_bw="32" op_8_bw="0" op_9_bw="0" op_10_bw="0" op_11_bw="32" op_12_bw="32" op_13_bw="32" op_14_bw="32" op_15_bw="0" op_16_bw="0">
<![CDATA[
:13  call void (...)* @_ssdm_op_SpecInterface(i8* %in_V, [5 x i8]* @p_str5, i32 1, i32 1, [5 x i8]* @p_str6, i32 0, i32 0, [1 x i8]* @p_str, [1 x i8]* @p_str, [1 x i8]* @p_str, i32 0, i32 0, i32 0, i32 0, [1 x i8]* @p_str, [1 x i8]* @p_str) nounwind

]]></Node>
<StgValue><ssdm name="specinterface_ln377"/></StgValue>
</operation>

<operation id="22" st_id="1" stage="1" lat="1">
<core>NULL</core>
<MemPortIdVec></MemPortIdVec>
<condition id="-1">
<or_exp><and_exp></and_exp></or_exp>
</condition>

<Node id="33" bw="0" op_0_bw="0" op_1_bw="16" op_2_bw="0" op_3_bw="32" op_4_bw="32" op_5_bw="0" op_6_bw="32" op_7_bw="32" op_8_bw="0" op_9_bw="0" op_10_bw="0" op_11_bw="32" op_12_bw="32" op_13_bw="32" op_14_bw="32" op_15_bw="0" op_16_bw="0">
<![CDATA[
:14  call void (...)* @_ssdm_op_SpecInterface(i16* %out_V, [5 x i8]* @p_str5, i32 1, i32 1, [5 x i8]* @p_str6, i32 0, i32 0, [1 x i8]* @p_str, [1 x i8]* @p_str, [1 x i8]* @p_str, i32 0, i32 0, i32 0, i32 0, [1 x i8]* @p_str, [1 x i8]* @p_str) nounwind

]]></Node>
<StgValue><ssdm name="specinterface_ln378"/></StgValue>
</operation>

<operation id="23" st_id="1" stage="1" lat="1">
<core>NULL</core>
<MemPortIdVec></MemPortIdVec>
<condition id="-1">
<or_exp><and_exp></and_exp></or_exp>
</condition>

<Node id="34" bw="0" op_0_bw="0">
<![CDATA[
:15  br label %1

]]></Node>
<StgValue><ssdm name="br_ln392"/></StgValue>
</operation>
</state>

<state id="2" st_id="2">

<operation id="24" st_id="2" stage="1" lat="1">
<core>NULL</core>
<MemPortIdVec></MemPortIdVec>
<condition id="-1">
<or_exp><and_exp></and_exp></or_exp>
</condition>

<Node id="36" bw="7" op_0_bw="7" op_1_bw="0" op_2_bw="7" op_3_bw="0">
<![CDATA[
:0  %i_0 = phi i7 [ 0, %0 ], [ %i_2, %3 ]

]]></Node>
<StgValue><ssdm name="i_0"/></StgValue>
</operation>

<operation id="25" st_id="2" stage="1" lat="1">
<core>Cmp</core>
<MemPortIdVec></MemPortIdVec>
<condition id="-1">
<or_exp><and_exp></and_exp></or_exp>
</condition>

<Node id="37" bw="1" op_0_bw="7" op_1_bw="7">
<![CDATA[
:1  %icmp_ln392 = icmp eq i7 %i_0, -64

]]></Node>
<StgValue><ssdm name="icmp_ln392"/></StgValue>
</operation>

<operation id="26" st_id="2" stage="1" lat="1">
<core>NULL</core>
<MemPortIdVec></MemPortIdVec>
<condition id="-1">
<or_exp><and_exp></and_exp></or_exp>
</condition>

<Node id="38" bw="32" op_0_bw="32" op_1_bw="64" op_2_bw="64" op_3_bw="64">
<![CDATA[
:2  %empty = call i32 (...)* @_ssdm_op_SpecLoopTripCount(i64 64, i64 64, i64 64)

]]></Node>
<StgValue><ssdm name="empty"/></StgValue>
</operation>

<operation id="27" st_id="2" stage="1" lat="1">
<core>AddSub</core>
<MemPortIdVec></MemPortIdVec>
<condition id="-1">
<or_exp><and_exp></and_exp></or_exp>
</condition>

<Node id="39" bw="7" op_0_bw="7" op_1_bw="7">
<![CDATA[
:3  %i_2 = add i7 %i_0, 1

]]></Node>
<StgValue><ssdm name="i_2"/></StgValue>
</operation>

<operation id="28" st_id="2" stage="1" lat="1">
<core>NULL</core>
<MemPortIdVec></MemPortIdVec>
<condition id="-1">
<or_exp><and_exp></and_exp></or_exp>
</condition>

<Node id="40" bw="0" op_0_bw="1" op_1_bw="0" op_2_bw="0">
<![CDATA[
:4  br i1 %icmp_ln392, label %4, label %2

]]></Node>
<StgValue><ssdm name="br_ln392"/></StgValue>
</operation>

<operation id="29" st_id="2" stage="1" lat="1">
<core>NULL</core>
<MemPortIdVec></MemPortIdVec>
<condition id="-1">
<or_exp><and_exp><literal name="icmp_ln392" val="0"/>
</and_exp></or_exp>
</condition>

<Node id="42" bw="0" op_0_bw="0" op_1_bw="0">
<![CDATA[
:0  call void (...)* @_ssdm_op_SpecLoopName([12 x i8]* @p_str7) nounwind

]]></Node>
<StgValue><ssdm name="specloopname_ln393"/></StgValue>
</operation>

<operation id="30" st_id="2" stage="1" lat="1">
<core>AXI4Stream</core>
<MemPortIdVec></MemPortIdVec>
<condition id="-1">
<or_exp><and_exp><literal name="icmp_ln392" val="0"/>
</and_exp></or_exp>
</condition>

<Node id="43" bw="8" op_0_bw="8" op_1_bw="8">
<![CDATA[
:1  %tmp = call i8 @_ssdm_op_Read.axis.volatile.i8P(i8* %in_V)

]]></Node>
<StgValue><ssdm name="tmp"/></StgValue>
</operation>

<operation id="31" st_id="2" stage="1" lat="1">
<core>NULL</core>
<MemPortIdVec></MemPortIdVec>
<condition id="-1">
<or_exp><and_exp><literal name="icmp_ln392" val="0"/>
</and_exp></or_exp>
</condition>

<Node id="44" bw="3" op_0_bw="7">
<![CDATA[
:2  %trunc_ln394 = trunc i7 %i_0 to i3

]]></Node>
<StgValue><ssdm name="trunc_ln394"/></StgValue>
</operation>

<operation id="32" st_id="2" stage="1" lat="1">
<core>NULL</core>
<MemPortIdVec></MemPortIdVec>
<condition id="-1">
<or_exp><and_exp><literal name="icmp_ln392" val="0"/>
</and_exp></or_exp>
</condition>

<Node id="45" bw="4" op_0_bw="4" op_1_bw="7" op_2_bw="32" op_3_bw="32">
<![CDATA[
:3  %lshr_ln = call i4 @_ssdm_op_PartSelect.i4.i7.i32.i32(i7 %i_0, i32 3, i32 6)

]]></Node>
<StgValue><ssdm name="lshr_ln"/></StgValue>
</operation>

<operation id="33" st_id="2" stage="1" lat="1">
<core>NULL</core>
<MemPortIdVec></MemPortIdVec>
<condition id="-1">
<or_exp><and_exp><literal name="icmp_ln392" val="0"/>
</and_exp></or_exp>
</condition>

<Node id="46" bw="64" op_0_bw="4">
<![CDATA[
:4  %zext_ln394 = zext i4 %lshr_ln to i64

]]></Node>
<StgValue><ssdm name="zext_ln394"/></StgValue>
</operation>

<operation id="34" st_id="2" stage="1" lat="1">
<core>NULL</core>
<MemPortIdVec></MemPortIdVec>
<condition id="-1">
<or_exp><and_exp><literal name="icmp_ln392" val="0"/>
</and_exp></or_exp>
</condition>

<Node id="47" bw="3" op_0_bw="8" op_1_bw="64" op_2_bw="64">
<![CDATA[
:5  %sample_0_addr = getelementptr [8 x i8]* %sample_0, i64 0, i64 %zext_ln394

]]></Node>
<StgValue><ssdm name="sample_0_addr"/></StgValue>
</operation>

<operation id="35" st_id="2" stage="1" lat="1">
<core>NULL</core>
<MemPortIdVec></MemPortIdVec>
<condition id="-1">
<or_exp><and_exp><literal name="icmp_ln392" val="0"/>
</and_exp></or_exp>
</condition>

<Node id="48" bw="3" op_0_bw="8" op_1_bw="64" op_2_bw="64">
<![CDATA[
:6  %sample_1_addr = getelementptr [8 x i8]* %sample_1, i64 0, i64 %zext_ln394

]]></Node>
<StgValue><ssdm name="sample_1_addr"/></StgValue>
</operation>

<operation id="36" st_id="2" stage="1" lat="1">
<core>NULL</core>
<MemPortIdVec></MemPortIdVec>
<condition id="-1">
<or_exp><and_exp><literal name="icmp_ln392" val="0"/>
</and_exp></or_exp>
</condition>

<Node id="49" bw="3" op_0_bw="8" op_1_bw="64" op_2_bw="64">
<![CDATA[
:7  %sample_2_addr = getelementptr [8 x i8]* %sample_2, i64 0, i64 %zext_ln394

]]></Node>
<StgValue><ssdm name="sample_2_addr"/></StgValue>
</operation>

<operation id="37" st_id="2" stage="1" lat="1">
<core>NULL</core>
<MemPortIdVec></MemPortIdVec>
<condition id="-1">
<or_exp><and_exp><literal name="icmp_ln392" val="0"/>
</and_exp></or_exp>
</condition>

<Node id="50" bw="3" op_0_bw="8" op_1_bw="64" op_2_bw="64">
<![CDATA[
:8  %sample_3_addr = getelementptr [8 x i8]* %sample_3, i64 0, i64 %zext_ln394

]]></Node>
<StgValue><ssdm name="sample_3_addr"/></StgValue>
</operation>

<operation id="38" st_id="2" stage="1" lat="1">
<core>NULL</core>
<MemPortIdVec></MemPortIdVec>
<condition id="-1">
<or_exp><and_exp><literal name="icmp_ln392" val="0"/>
</and_exp></or_exp>
</condition>

<Node id="51" bw="3" op_0_bw="8" op_1_bw="64" op_2_bw="64">
<![CDATA[
:9  %sample_4_addr = getelementptr [8 x i8]* %sample_4, i64 0, i64 %zext_ln394

]]></Node>
<StgValue><ssdm name="sample_4_addr"/></StgValue>
</operation>

<operation id="39" st_id="2" stage="1" lat="1">
<core>NULL</core>
<MemPortIdVec></MemPortIdVec>
<condition id="-1">
<or_exp><and_exp><literal name="icmp_ln392" val="0"/>
</and_exp></or_exp>
</condition>

<Node id="52" bw="3" op_0_bw="8" op_1_bw="64" op_2_bw="64">
<![CDATA[
:10  %sample_5_addr = getelementptr [8 x i8]* %sample_5, i64 0, i64 %zext_ln394

]]></Node>
<StgValue><ssdm name="sample_5_addr"/></StgValue>
</operation>

<operation id="40" st_id="2" stage="1" lat="1">
<core>NULL</core>
<MemPortIdVec></MemPortIdVec>
<condition id="-1">
<or_exp><and_exp><literal name="icmp_ln392" val="0"/>
</and_exp></or_exp>
</condition>

<Node id="53" bw="3" op_0_bw="8" op_1_bw="64" op_2_bw="64">
<![CDATA[
:11  %sample_6_addr = getelementptr [8 x i8]* %sample_6, i64 0, i64 %zext_ln394

]]></Node>
<StgValue><ssdm name="sample_6_addr"/></StgValue>
</operation>

<operation id="41" st_id="2" stage="1" lat="1">
<core>NULL</core>
<MemPortIdVec></MemPortIdVec>
<condition id="-1">
<or_exp><and_exp><literal name="icmp_ln392" val="0"/>
</and_exp></or_exp>
</condition>

<Node id="54" bw="3" op_0_bw="8" op_1_bw="64" op_2_bw="64">
<![CDATA[
:12  %sample_7_addr = getelementptr [8 x i8]* %sample_7, i64 0, i64 %zext_ln394

]]></Node>
<StgValue><ssdm name="sample_7_addr"/></StgValue>
</operation>

<operation id="42" st_id="2" stage="1" lat="1">
<core>NULL</core>
<MemPortIdVec></MemPortIdVec>
<condition id="-1">
<or_exp><and_exp><literal name="icmp_ln392" val="0"/>
</and_exp></or_exp>
</condition>

<Node id="55" bw="0" op_0_bw="3" op_1_bw="0" op_2_bw="3" op_3_bw="0" op_4_bw="3" op_5_bw="0" op_6_bw="3" op_7_bw="0" op_8_bw="3" op_9_bw="0" op_10_bw="3" op_11_bw="0" op_12_bw="3" op_13_bw="0" op_14_bw="3" op_15_bw="0">
<![CDATA[
:13  switch i3 %trunc_ln394, label %branch7 [
    i3 0, label %branch0
    i3 1, label %branch1
    i3 2, label %branch2
    i3 3, label %branch3
    i3 -4, label %branch4
    i3 -3, label %branch5
    i3 -2, label %branch6
  ]

]]></Node>
<StgValue><ssdm name="switch_ln394"/></StgValue>
</operation>

<operation id="43" st_id="2" stage="1" lat="1">
<core>RAM</core>
<MemPortIdVec>0 </MemPortIdVec>
<condition id="-1">
<or_exp><and_exp><literal name="icmp_ln392" val="0"/>
<literal name="trunc_ln394" val="-2"/>
</and_exp></or_exp>
</condition>

<Node id="57" bw="0" op_0_bw="8" op_1_bw="3">
<![CDATA[
branch6:0  store i8 %tmp, i8* %sample_6_addr, align 1

]]></Node>
<StgValue><ssdm name="store_ln394"/></StgValue>
</operation>

<operation id="44" st_id="2" stage="1" lat="1">
<core>NULL</core>
<MemPortIdVec></MemPortIdVec>
<condition id="-1">
<or_exp><and_exp><literal name="icmp_ln392" val="0"/>
<literal name="trunc_ln394" val="-2"/>
</and_exp></or_exp>
</condition>

<Node id="58" bw="0" op_0_bw="0">
<![CDATA[
branch6:1  br label %3

]]></Node>
<StgValue><ssdm name="br_ln394"/></StgValue>
</operation>

<operation id="45" st_id="2" stage="1" lat="1">
<core>RAM</core>
<MemPortIdVec>0 </MemPortIdVec>
<condition id="-1">
<or_exp><and_exp><literal name="icmp_ln392" val="0"/>
<literal name="trunc_ln394" val="-3"/>
</and_exp></or_exp>
</condition>

<Node id="60" bw="0" op_0_bw="8" op_1_bw="3">
<![CDATA[
branch5:0  store i8 %tmp, i8* %sample_5_addr, align 1

]]></Node>
<StgValue><ssdm name="store_ln394"/></StgValue>
</operation>

<operation id="46" st_id="2" stage="1" lat="1">
<core>NULL</core>
<MemPortIdVec></MemPortIdVec>
<condition id="-1">
<or_exp><and_exp><literal name="icmp_ln392" val="0"/>
<literal name="trunc_ln394" val="-3"/>
</and_exp></or_exp>
</condition>

<Node id="61" bw="0" op_0_bw="0">
<![CDATA[
branch5:1  br label %3

]]></Node>
<StgValue><ssdm name="br_ln394"/></StgValue>
</operation>

<operation id="47" st_id="2" stage="1" lat="1">
<core>RAM</core>
<MemPortIdVec>0 </MemPortIdVec>
<condition id="-1">
<or_exp><and_exp><literal name="icmp_ln392" val="0"/>
<literal name="trunc_ln394" val="-4"/>
</and_exp></or_exp>
</condition>

<Node id="63" bw="0" op_0_bw="8" op_1_bw="3">
<![CDATA[
branch4:0  store i8 %tmp, i8* %sample_4_addr, align 1

]]></Node>
<StgValue><ssdm name="store_ln394"/></StgValue>
</operation>

<operation id="48" st_id="2" stage="1" lat="1">
<core>NULL</core>
<MemPortIdVec></MemPortIdVec>
<condition id="-1">
<or_exp><and_exp><literal name="icmp_ln392" val="0"/>
<literal name="trunc_ln394" val="-4"/>
</and_exp></or_exp>
</condition>

<Node id="64" bw="0" op_0_bw="0">
<![CDATA[
branch4:1  br label %3

]]></Node>
<StgValue><ssdm name="br_ln394"/></StgValue>
</operation>

<operation id="49" st_id="2" stage="1" lat="1">
<core>RAM</core>
<MemPortIdVec>0 </MemPortIdVec>
<condition id="-1">
<or_exp><and_exp><literal name="icmp_ln392" val="0"/>
<literal name="trunc_ln394" val="3"/>
</and_exp></or_exp>
</condition>

<Node id="66" bw="0" op_0_bw="8" op_1_bw="3">
<![CDATA[
branch3:0  store i8 %tmp, i8* %sample_3_addr, align 1

]]></Node>
<StgValue><ssdm name="store_ln394"/></StgValue>
</operation>

<operation id="50" st_id="2" stage="1" lat="1">
<core>NULL</core>
<MemPortIdVec></MemPortIdVec>
<condition id="-1">
<or_exp><and_exp><literal name="icmp_ln392" val="0"/>
<literal name="trunc_ln394" val="3"/>
</and_exp></or_exp>
</condition>

<Node id="67" bw="0" op_0_bw="0">
<![CDATA[
branch3:1  br label %3

]]></Node>
<StgValue><ssdm name="br_ln394"/></StgValue>
</operation>

<operation id="51" st_id="2" stage="1" lat="1">
<core>RAM</core>
<MemPortIdVec>0 </MemPortIdVec>
<condition id="-1">
<or_exp><and_exp><literal name="icmp_ln392" val="0"/>
<literal name="trunc_ln394" val="2"/>
</and_exp></or_exp>
</condition>

<Node id="69" bw="0" op_0_bw="8" op_1_bw="3">
<![CDATA[
branch2:0  store i8 %tmp, i8* %sample_2_addr, align 1

]]></Node>
<StgValue><ssdm name="store_ln394"/></StgValue>
</operation>

<operation id="52" st_id="2" stage="1" lat="1">
<core>NULL</core>
<MemPortIdVec></MemPortIdVec>
<condition id="-1">
<or_exp><and_exp><literal name="icmp_ln392" val="0"/>
<literal name="trunc_ln394" val="2"/>
</and_exp></or_exp>
</condition>

<Node id="70" bw="0" op_0_bw="0">
<![CDATA[
branch2:1  br label %3

]]></Node>
<StgValue><ssdm name="br_ln394"/></StgValue>
</operation>

<operation id="53" st_id="2" stage="1" lat="1">
<core>RAM</core>
<MemPortIdVec>0 </MemPortIdVec>
<condition id="-1">
<or_exp><and_exp><literal name="icmp_ln392" val="0"/>
<literal name="trunc_ln394" val="1"/>
</and_exp></or_exp>
</condition>

<Node id="72" bw="0" op_0_bw="8" op_1_bw="3">
<![CDATA[
branch1:0  store i8 %tmp, i8* %sample_1_addr, align 1

]]></Node>
<StgValue><ssdm name="store_ln394"/></StgValue>
</operation>

<operation id="54" st_id="2" stage="1" lat="1">
<core>NULL</core>
<MemPortIdVec></MemPortIdVec>
<condition id="-1">
<or_exp><and_exp><literal name="icmp_ln392" val="0"/>
<literal name="trunc_ln394" val="1"/>
</and_exp></or_exp>
</condition>

<Node id="73" bw="0" op_0_bw="0">
<![CDATA[
branch1:1  br label %3

]]></Node>
<StgValue><ssdm name="br_ln394"/></StgValue>
</operation>

<operation id="55" st_id="2" stage="1" lat="1">
<core>RAM</core>
<MemPortIdVec>0 </MemPortIdVec>
<condition id="-1">
<or_exp><and_exp><literal name="icmp_ln392" val="0"/>
<literal name="trunc_ln394" val="0"/>
</and_exp></or_exp>
</condition>

<Node id="75" bw="0" op_0_bw="8" op_1_bw="3">
<![CDATA[
branch0:0  store i8 %tmp, i8* %sample_0_addr, align 1

]]></Node>
<StgValue><ssdm name="store_ln394"/></StgValue>
</operation>

<operation id="56" st_id="2" stage="1" lat="1">
<core>NULL</core>
<MemPortIdVec></MemPortIdVec>
<condition id="-1">
<or_exp><and_exp><literal name="icmp_ln392" val="0"/>
<literal name="trunc_ln394" val="0"/>
</and_exp></or_exp>
</condition>

<Node id="76" bw="0" op_0_bw="0">
<![CDATA[
branch0:1  br label %3

]]></Node>
<StgValue><ssdm name="br_ln394"/></StgValue>
</operation>

<operation id="57" st_id="2" stage="1" lat="1">
<core>RAM</core>
<MemPortIdVec>0 </MemPortIdVec>
<condition id="-1">
<or_exp><and_exp><literal name="icmp_ln392" val="0"/>
<literal name="trunc_ln394" val="-1"/>
</and_exp></or_exp>
</condition>

<Node id="78" bw="0" op_0_bw="8" op_1_bw="3">
<![CDATA[
branch7:0  store i8 %tmp, i8* %sample_7_addr, align 1

]]></Node>
<StgValue><ssdm name="store_ln394"/></StgValue>
</operation>

<operation id="58" st_id="2" stage="1" lat="1">
<core>NULL</core>
<MemPortIdVec></MemPortIdVec>
<condition id="-1">
<or_exp><and_exp><literal name="icmp_ln392" val="0"/>
<literal name="trunc_ln394" val="-1"/>
</and_exp></or_exp>
</condition>

<Node id="79" bw="0" op_0_bw="0">
<![CDATA[
branch7:1  br label %3

]]></Node>
<StgValue><ssdm name="br_ln394"/></StgValue>
</operation>

<operation id="59" st_id="2" stage="2" lat="2">
<core></core>
<MemPortIdVec></MemPortIdVec>
<condition id="-1">
<or_exp><and_exp><literal name="icmp_ln392" val="1"/>
</and_exp></or_exp>
</condition>

<Node id="83" bw="0" op_0_bw="0" op_1_bw="8" op_2_bw="8" op_3_bw="8" op_4_bw="8" op_5_bw="8" op_6_bw="8" op_7_bw="8" op_8_bw="8" op_9_bw="16" op_10_bw="16" op_11_bw="8" op_12_bw="8" op_13_bw="8" op_14_bw="8" op_15_bw="8" op_16_bw="8" op_17_bw="8" op_18_bw="8">
<![CDATA[
:0  call fastcc void @mlp_kernel([8 x i8]* %sample_0, [8 x i8]* %sample_1, [8 x i8]* %sample_2, [8 x i8]* %sample_3, [8 x i8]* %sample_4, [8 x i8]* %sample_5, [8 x i8]* %sample_6, [8 x i8]* %sample_7, [5 x i16]* %prediction_0, [5 x i16]* %prediction_1)

]]></Node>
<StgValue><ssdm name="call_ln398"/></StgValue>
</operation>
</state>

<state id="3" st_id="3">

<operation id="60" st_id="3" stage="1" lat="1">
<core>NULL</core>
<MemPortIdVec></MemPortIdVec>
<condition id="-1">
<or_exp><and_exp></and_exp></or_exp>
</condition>

<Node id="81" bw="0" op_0_bw="0">
<![CDATA[
:0  br label %1

]]></Node>
<StgValue><ssdm name="br_ln392"/></StgValue>
</operation>
</state>

<state id="4" st_id="4">

<operation id="61" st_id="4" stage="1" lat="2">
<core></core>
<MemPortIdVec></MemPortIdVec>
<condition id="-1">
<or_exp><and_exp></and_exp></or_exp>
</condition>

<Node id="83" bw="0" op_0_bw="0" op_1_bw="8" op_2_bw="8" op_3_bw="8" op_4_bw="8" op_5_bw="8" op_6_bw="8" op_7_bw="8" op_8_bw="8" op_9_bw="16" op_10_bw="16" op_11_bw="8" op_12_bw="8" op_13_bw="8" op_14_bw="8" op_15_bw="8" op_16_bw="8" op_17_bw="8" op_18_bw="8">
<![CDATA[
:0  call fastcc void @mlp_kernel([8 x i8]* %sample_0, [8 x i8]* %sample_1, [8 x i8]* %sample_2, [8 x i8]* %sample_3, [8 x i8]* %sample_4, [8 x i8]* %sample_5, [8 x i8]* %sample_6, [8 x i8]* %sample_7, [5 x i16]* %prediction_0, [5 x i16]* %prediction_1)

]]></Node>
<StgValue><ssdm name="call_ln398"/></StgValue>
</operation>

<operation id="62" st_id="4" stage="1" lat="1">
<core>NULL</core>
<MemPortIdVec></MemPortIdVec>
<condition id="-1">
<or_exp><and_exp></and_exp></or_exp>
</condition>

<Node id="84" bw="0" op_0_bw="0">
<![CDATA[
:1  br label %5

]]></Node>
<StgValue><ssdm name="br_ln401"/></StgValue>
</operation>
</state>

<state id="5" st_id="5">

<operation id="63" st_id="5" stage="1" lat="1">
<core>NULL</core>
<MemPortIdVec></MemPortIdVec>
<condition id="-1">
<or_exp><and_exp></and_exp></or_exp>
</condition>

<Node id="86" bw="4" op_0_bw="4" op_1_bw="0" op_2_bw="4" op_3_bw="0">
<![CDATA[
:0  %i1_0 = phi i4 [ 0, %4 ], [ %i, %_ifconv ]

]]></Node>
<StgValue><ssdm name="i1_0"/></StgValue>
</operation>

<operation id="64" st_id="5" stage="1" lat="1">
<core>Cmp</core>
<MemPortIdVec></MemPortIdVec>
<condition id="-1">
<or_exp><and_exp></and_exp></or_exp>
</condition>

<Node id="87" bw="1" op_0_bw="4" op_1_bw="4">
<![CDATA[
:1  %icmp_ln401 = icmp eq i4 %i1_0, -6

]]></Node>
<StgValue><ssdm name="icmp_ln401"/></StgValue>
</operation>

<operation id="65" st_id="5" stage="1" lat="1">
<core>NULL</core>
<MemPortIdVec></MemPortIdVec>
<condition id="-1">
<or_exp><and_exp></and_exp></or_exp>
</condition>

<Node id="88" bw="32" op_0_bw="32" op_1_bw="64" op_2_bw="64" op_3_bw="64">
<![CDATA[
:2  %empty_16 = call i32 (...)* @_ssdm_op_SpecLoopTripCount(i64 10, i64 10, i64 10)

]]></Node>
<StgValue><ssdm name="empty_16"/></StgValue>
</operation>

<operation id="66" st_id="5" stage="1" lat="1">
<core>AddSub</core>
<MemPortIdVec></MemPortIdVec>
<condition id="-1">
<or_exp><and_exp></and_exp></or_exp>
</condition>

<Node id="89" bw="4" op_0_bw="4" op_1_bw="4">
<![CDATA[
:3  %i = add i4 %i1_0, 1

]]></Node>
<StgValue><ssdm name="i"/></StgValue>
</operation>

<operation id="67" st_id="5" stage="1" lat="1">
<core>NULL</core>
<MemPortIdVec></MemPortIdVec>
<condition id="-1">
<or_exp><and_exp></and_exp></or_exp>
</condition>

<Node id="90" bw="0" op_0_bw="1" op_1_bw="0" op_2_bw="0">
<![CDATA[
:4  br i1 %icmp_ln401, label %6, label %_ifconv

]]></Node>
<StgValue><ssdm name="br_ln401"/></StgValue>
</operation>

<operation id="68" st_id="5" stage="1" lat="1">
<core>NULL</core>
<MemPortIdVec></MemPortIdVec>
<condition id="-1">
<or_exp><and_exp><literal name="icmp_ln401" val="0"/>
</and_exp></or_exp>
</condition>

<Node id="93" bw="1" op_0_bw="4">
<![CDATA[
_ifconv:1  %trunc_ln403 = trunc i4 %i1_0 to i1

]]></Node>
<StgValue><ssdm name="trunc_ln403"/></StgValue>
</operation>

<operation id="69" st_id="5" stage="1" lat="1">
<core>NULL</core>
<MemPortIdVec></MemPortIdVec>
<condition id="-1">
<or_exp><and_exp><literal name="icmp_ln401" val="0"/>
</and_exp></or_exp>
</condition>

<Node id="94" bw="3" op_0_bw="3" op_1_bw="4" op_2_bw="32" op_3_bw="32">
<![CDATA[
_ifconv:2  %lshr_ln4 = call i3 @_ssdm_op_PartSelect.i3.i4.i32.i32(i4 %i1_0, i32 1, i32 3)

]]></Node>
<StgValue><ssdm name="lshr_ln4"/></StgValue>
</operation>

<operation id="70" st_id="5" stage="1" lat="1">
<core>NULL</core>
<MemPortIdVec></MemPortIdVec>
<condition id="-1">
<or_exp><and_exp><literal name="icmp_ln401" val="0"/>
</and_exp></or_exp>
</condition>

<Node id="95" bw="64" op_0_bw="3">
<![CDATA[
_ifconv:3  %zext_ln403 = zext i3 %lshr_ln4 to i64

]]></Node>
<StgValue><ssdm name="zext_ln403"/></StgValue>
</operation>

<operation id="71" st_id="5" stage="1" lat="1">
<core>NULL</core>
<MemPortIdVec></MemPortIdVec>
<condition id="-1">
<or_exp><and_exp><literal name="icmp_ln401" val="0"/>
</and_exp></or_exp>
</condition>

<Node id="96" bw="3" op_0_bw="16" op_1_bw="64" op_2_bw="64">
<![CDATA[
_ifconv:4  %prediction_0_addr = getelementptr [5 x i16]* %prediction_0, i64 0, i64 %zext_ln403

]]></Node>
<StgValue><ssdm name="prediction_0_addr"/></StgValue>
</operation>

<operation id="72" st_id="5" stage="1" lat="1">
<core>NULL</core>
<MemPortIdVec></MemPortIdVec>
<condition id="-1">
<or_exp><and_exp><literal name="icmp_ln401" val="0"/>
</and_exp></or_exp>
</condition>

<Node id="97" bw="3" op_0_bw="16" op_1_bw="64" op_2_bw="64">
<![CDATA[
_ifconv:5  %prediction_1_addr = getelementptr [5 x i16]* %prediction_1, i64 0, i64 %zext_ln403

]]></Node>
<StgValue><ssdm name="prediction_1_addr"/></StgValue>
</operation>

<operation id="73" st_id="5" stage="2" lat="2">
<core>RAM</core>
<MemPortIdVec>0 </MemPortIdVec>
<condition id="-1">
<or_exp><and_exp><literal name="icmp_ln401" val="0"/>
</and_exp></or_exp>
</condition>

<Node id="98" bw="16" op_0_bw="3">
<![CDATA[
_ifconv:6  %prediction_1_load = load i16* %prediction_1_addr, align 2

]]></Node>
<StgValue><ssdm name="prediction_1_load"/></StgValue>
</operation>

<operation id="74" st_id="5" stage="2" lat="2">
<core>RAM</core>
<MemPortIdVec>0 </MemPortIdVec>
<condition id="-1">
<or_exp><and_exp><literal name="icmp_ln401" val="0"/>
</and_exp></or_exp>
</condition>

<Node id="99" bw="16" op_0_bw="3">
<![CDATA[
_ifconv:7  %prediction_0_load = load i16* %prediction_0_addr, align 2

]]></Node>
<StgValue><ssdm name="prediction_0_load"/></StgValue>
</operation>

<operation id="75" st_id="5" stage="1" lat="1">
<core>NULL</core>
<MemPortIdVec></MemPortIdVec>
<condition id="-1">
<or_exp><and_exp><literal name="icmp_ln401" val="1"/>
</and_exp></or_exp>
</condition>

<Node id="104" bw="0">
<![CDATA[
:0  ret void

]]></Node>
<StgValue><ssdm name="ret_ln405"/></StgValue>
</operation>
</state>

<state id="6" st_id="6">

<operation id="76" st_id="6" stage="1" lat="2">
<core>RAM</core>
<MemPortIdVec>0 </MemPortIdVec>
<condition id="-1">
<or_exp><and_exp></and_exp></or_exp>
</condition>

<Node id="98" bw="16" op_0_bw="3">
<![CDATA[
_ifconv:6  %prediction_1_load = load i16* %prediction_1_addr, align 2

]]></Node>
<StgValue><ssdm name="prediction_1_load"/></StgValue>
</operation>

<operation id="77" st_id="6" stage="1" lat="2">
<core>RAM</core>
<MemPortIdVec>0 </MemPortIdVec>
<condition id="-1">
<or_exp><and_exp></and_exp></or_exp>
</condition>

<Node id="99" bw="16" op_0_bw="3">
<![CDATA[
_ifconv:7  %prediction_0_load = load i16* %prediction_0_addr, align 2

]]></Node>
<StgValue><ssdm name="prediction_0_load"/></StgValue>
</operation>

<operation id="78" st_id="6" stage="1" lat="1">
<core>Sel</core>
<MemPortIdVec></MemPortIdVec>
<condition id="-1">
<or_exp><and_exp></and_exp></or_exp>
</condition>

<Node id="100" bw="16" op_0_bw="1" op_1_bw="16" op_2_bw="16">
<![CDATA[
_ifconv:8  %tmp_4 = select i1 %trunc_ln403, i16 %prediction_1_load, i16 %prediction_0_load

]]></Node>
<StgValue><ssdm name="tmp_4"/></StgValue>
</operation>

<operation id="79" st_id="6" stage="2" lat="2">
<core>AXI4Stream</core>
<MemPortIdVec></MemPortIdVec>
<condition id="-1">
<or_exp><and_exp></and_exp></or_exp>
</condition>

<Node id="101" bw="0" op_0_bw="0" op_1_bw="16" op_2_bw="16">
<![CDATA[
_ifconv:9  call void @_ssdm_op_Write.axis.volatile.i16P(i16* %out_V, i16 %tmp_4)

]]></Node>
<StgValue><ssdm name="write_ln403"/></StgValue>
</operation>
</state>

<state id="7" st_id="7">

<operation id="80" st_id="7" stage="1" lat="1">
<core>NULL</core>
<MemPortIdVec></MemPortIdVec>
<condition id="-1">
<or_exp><and_exp></and_exp></or_exp>
</condition>

<Node id="92" bw="0" op_0_bw="0" op_1_bw="0">
<![CDATA[
_ifconv:0  call void (...)* @_ssdm_op_SpecLoopName([17 x i8]* @p_str8) nounwind

]]></Node>
<StgValue><ssdm name="specloopname_ln402"/></StgValue>
</operation>

<operation id="81" st_id="7" stage="1" lat="2">
<core>AXI4Stream</core>
<MemPortIdVec></MemPortIdVec>
<condition id="-1">
<or_exp><and_exp></and_exp></or_exp>
</condition>

<Node id="101" bw="0" op_0_bw="0" op_1_bw="16" op_2_bw="16">
<![CDATA[
_ifconv:9  call void @_ssdm_op_Write.axis.volatile.i16P(i16* %out_V, i16 %tmp_4)

]]></Node>
<StgValue><ssdm name="write_ln403"/></StgValue>
</operation>

<operation id="82" st_id="7" stage="1" lat="1">
<core>NULL</core>
<MemPortIdVec></MemPortIdVec>
<condition id="-1">
<or_exp><and_exp></and_exp></or_exp>
</condition>

<Node id="102" bw="0" op_0_bw="0">
<![CDATA[
_ifconv:10  br label %5

]]></Node>
<StgValue><ssdm name="br_ln401"/></StgValue>
</operation>
</state>
</state_list>


<ports>
<port id="100" name="in_V" dir="0" iftype="0">
<core>NULL</core><StgValue><ssdm name="in_V"/></StgValue>
</port>
<port id="101" name="out_V" dir="1" iftype="0">
<core>NULL</core><StgValue><ssdm name="out_V"/></StgValue>
</port>
<port id="102" name="l1_weights_1" dir="0" iftype="1">
<core>RAM_2P_BRAM</core><StgValue><ssdm name="l1_weights_1"/><MemPortTyVec>1 3 </MemPortTyVec>
</StgValue>
</port>
<port id="103" name="l1_weights_0" dir="0" iftype="1">
<core>RAM_2P_BRAM</core><StgValue><ssdm name="l1_weights_0"/><MemPortTyVec>1 3 </MemPortTyVec>
</StgValue>
</port>
<port id="104" name="l1_biases_1" dir="0" iftype="1">
<core>ROM_nP</core><StgValue><ssdm name="l1_biases_1"/><MemPortTyVec>1 </MemPortTyVec>
</StgValue>
</port>
<port id="105" name="l1_biases_0" dir="0" iftype="1">
<core>ROM_nP</core><StgValue><ssdm name="l1_biases_0"/><MemPortTyVec>1 </MemPortTyVec>
</StgValue>
</port>
<port id="106" name="l2_weights_1" dir="0" iftype="1">
<core>RAM_2P_BRAM</core><StgValue><ssdm name="l2_weights_1"/><MemPortTyVec>1 3 </MemPortTyVec>
</StgValue>
</port>
<port id="107" name="l2_weights_0" dir="0" iftype="1">
<core>RAM_2P_BRAM</core><StgValue><ssdm name="l2_weights_0"/><MemPortTyVec>1 3 </MemPortTyVec>
</StgValue>
</port>
<port id="108" name="l2_biases_1" dir="0" iftype="1">
<core>ROM_nP</core><StgValue><ssdm name="l2_biases_1"/><MemPortTyVec>1 </MemPortTyVec>
</StgValue>
</port>
<port id="109" name="l2_biases_0" dir="0" iftype="1">
<core>ROM_nP</core><StgValue><ssdm name="l2_biases_0"/><MemPortTyVec>1 </MemPortTyVec>
</StgValue>
</port>
</ports>


<dataflows>
<dataflow id="111" from="_ssdm_op_SpecBitsMap" to="specbitsmap_ln0" fromId="110" toId="8">
</dataflow>
<dataflow id="112" from="in_V" to="specbitsmap_ln0" fromId="100" toId="8">
</dataflow>
<dataflow id="113" from="_ssdm_op_SpecBitsMap" to="specbitsmap_ln0" fromId="110" toId="9">
</dataflow>
<dataflow id="114" from="out_V" to="specbitsmap_ln0" fromId="101" toId="9">
</dataflow>
<dataflow id="116" from="_ssdm_op_SpecTopModule" to="spectopmodule_ln0" fromId="115" toId="10">
</dataflow>
<dataflow id="118" from="mlp_str" to="spectopmodule_ln0" fromId="117" toId="10">
</dataflow>
<dataflow id="120" from="StgValue_119" to="sample_0" fromId="119" toId="11">
</dataflow>
<dataflow id="121" from="StgValue_119" to="sample_1" fromId="119" toId="12">
</dataflow>
<dataflow id="122" from="StgValue_119" to="sample_2" fromId="119" toId="13">
</dataflow>
<dataflow id="123" from="StgValue_119" to="sample_3" fromId="119" toId="14">
</dataflow>
<dataflow id="124" from="StgValue_119" to="sample_4" fromId="119" toId="15">
</dataflow>
<dataflow id="125" from="StgValue_119" to="sample_5" fromId="119" toId="16">
</dataflow>
<dataflow id="126" from="StgValue_119" to="sample_6" fromId="119" toId="17">
</dataflow>
<dataflow id="127" from="StgValue_119" to="sample_7" fromId="119" toId="18">
</dataflow>
<dataflow id="128" from="StgValue_119" to="prediction_0" fromId="119" toId="19">
</dataflow>
<dataflow id="129" from="StgValue_119" to="prediction_1" fromId="119" toId="20">
</dataflow>
<dataflow id="131" from="_ssdm_op_SpecInterface" to="specinterface_ln377" fromId="130" toId="21">
</dataflow>
<dataflow id="132" from="in_V" to="specinterface_ln377" fromId="100" toId="21">
</dataflow>
<dataflow id="134" from="p_str5" to="specinterface_ln377" fromId="133" toId="21">
</dataflow>
<dataflow id="136" from="StgValue_135" to="specinterface_ln377" fromId="135" toId="21">
</dataflow>
<dataflow id="137" from="StgValue_135" to="specinterface_ln377" fromId="135" toId="21">
</dataflow>
<dataflow id="139" from="p_str6" to="specinterface_ln377" fromId="138" toId="21">
</dataflow>
<dataflow id="141" from="StgValue_140" to="specinterface_ln377" fromId="140" toId="21">
</dataflow>
<dataflow id="142" from="StgValue_140" to="specinterface_ln377" fromId="140" toId="21">
</dataflow>
<dataflow id="144" from="p_str" to="specinterface_ln377" fromId="143" toId="21">
</dataflow>
<dataflow id="145" from="p_str" to="specinterface_ln377" fromId="143" toId="21">
</dataflow>
<dataflow id="146" from="p_str" to="specinterface_ln377" fromId="143" toId="21">
</dataflow>
<dataflow id="147" from="StgValue_140" to="specinterface_ln377" fromId="140" toId="21">
</dataflow>
<dataflow id="148" from="StgValue_140" to="specinterface_ln377" fromId="140" toId="21">
</dataflow>
<dataflow id="149" from="StgValue_140" to="specinterface_ln377" fromId="140" toId="21">
</dataflow>
<dataflow id="150" from="StgValue_140" to="specinterface_ln377" fromId="140" toId="21">
</dataflow>
<dataflow id="151" from="p_str" to="specinterface_ln377" fromId="143" toId="21">
</dataflow>
<dataflow id="152" from="p_str" to="specinterface_ln377" fromId="143" toId="21">
</dataflow>
<dataflow id="153" from="_ssdm_op_SpecInterface" to="specinterface_ln378" fromId="130" toId="22">
</dataflow>
<dataflow id="154" from="out_V" to="specinterface_ln378" fromId="101" toId="22">
</dataflow>
<dataflow id="155" from="p_str5" to="specinterface_ln378" fromId="133" toId="22">
</dataflow>
<dataflow id="156" from="StgValue_135" to="specinterface_ln378" fromId="135" toId="22">
</dataflow>
<dataflow id="157" from="StgValue_135" to="specinterface_ln378" fromId="135" toId="22">
</dataflow>
<dataflow id="158" from="p_str6" to="specinterface_ln378" fromId="138" toId="22">
</dataflow>
<dataflow id="159" from="StgValue_140" to="specinterface_ln378" fromId="140" toId="22">
</dataflow>
<dataflow id="160" from="StgValue_140" to="specinterface_ln378" fromId="140" toId="22">
</dataflow>
<dataflow id="161" from="p_str" to="specinterface_ln378" fromId="143" toId="22">
</dataflow>
<dataflow id="162" from="p_str" to="specinterface_ln378" fromId="143" toId="22">
</dataflow>
<dataflow id="163" from="p_str" to="specinterface_ln378" fromId="143" toId="22">
</dataflow>
<dataflow id="164" from="StgValue_140" to="specinterface_ln378" fromId="140" toId="22">
</dataflow>
<dataflow id="165" from="StgValue_140" to="specinterface_ln378" fromId="140" toId="22">
</dataflow>
<dataflow id="166" from="StgValue_140" to="specinterface_ln378" fromId="140" toId="22">
</dataflow>
<dataflow id="167" from="StgValue_140" to="specinterface_ln378" fromId="140" toId="22">
</dataflow>
<dataflow id="168" from="p_str" to="specinterface_ln378" fromId="143" toId="22">
</dataflow>
<dataflow id="169" from="p_str" to="specinterface_ln378" fromId="143" toId="22">
</dataflow>
<dataflow id="171" from="StgValue_170" to="i_0" fromId="170" toId="24">
<condition id="-1">
<or_exp><and_exp></and_exp></or_exp>
</condition>
</dataflow>
<dataflow id="172" from="br_ln392" to="i_0" fromId="23" toId="24">
</dataflow>
<dataflow id="173" from="i_2" to="i_0" fromId="27" toId="24">
<BackEdge/>
<condition id="-1">
<or_exp><and_exp></and_exp></or_exp>
</condition>
</dataflow>
<dataflow id="174" from="br_ln392" to="i_0" fromId="60" toId="24">
<BackEdge/>
</dataflow>
<dataflow id="175" from="i_0" to="icmp_ln392" fromId="24" toId="25">
</dataflow>
<dataflow id="177" from="StgValue_176" to="icmp_ln392" fromId="176" toId="25">
</dataflow>
<dataflow id="179" from="_ssdm_op_SpecLoopTripCount" to="empty" fromId="178" toId="26">
</dataflow>
<dataflow id="181" from="StgValue_180" to="empty" fromId="180" toId="26">
</dataflow>
<dataflow id="182" from="StgValue_180" to="empty" fromId="180" toId="26">
</dataflow>
<dataflow id="183" from="StgValue_180" to="empty" fromId="180" toId="26">
</dataflow>
<dataflow id="184" from="i_0" to="i_2" fromId="24" toId="27">
</dataflow>
<dataflow id="186" from="StgValue_185" to="i_2" fromId="185" toId="27">
</dataflow>
<dataflow id="187" from="icmp_ln392" to="br_ln392" fromId="25" toId="28">
</dataflow>
<dataflow id="189" from="_ssdm_op_SpecLoopName" to="specloopname_ln393" fromId="188" toId="29">
</dataflow>
<dataflow id="191" from="p_str7" to="specloopname_ln393" fromId="190" toId="29">
</dataflow>
<dataflow id="193" from="_ssdm_op_Read.axis.volatile.i8P" to="tmp" fromId="192" toId="30">
</dataflow>
<dataflow id="194" from="in_V" to="tmp" fromId="100" toId="30">
</dataflow>
<dataflow id="195" from="i_0" to="trunc_ln394" fromId="24" toId="31">
</dataflow>
<dataflow id="197" from="_ssdm_op_PartSelect.i4.i7.i32.i32" to="lshr_ln" fromId="196" toId="32">
</dataflow>
<dataflow id="198" from="i_0" to="lshr_ln" fromId="24" toId="32">
</dataflow>
<dataflow id="200" from="StgValue_199" to="lshr_ln" fromId="199" toId="32">
</dataflow>
<dataflow id="202" from="StgValue_201" to="lshr_ln" fromId="201" toId="32">
</dataflow>
<dataflow id="203" from="lshr_ln" to="zext_ln394" fromId="32" toId="33">
</dataflow>
<dataflow id="204" from="sample_0" to="sample_0_addr" fromId="11" toId="34">
</dataflow>
<dataflow id="206" from="StgValue_205" to="sample_0_addr" fromId="205" toId="34">
</dataflow>
<dataflow id="207" from="zext_ln394" to="sample_0_addr" fromId="33" toId="34">
</dataflow>
<dataflow id="208" from="sample_1" to="sample_1_addr" fromId="12" toId="35">
</dataflow>
<dataflow id="209" from="StgValue_205" to="sample_1_addr" fromId="205" toId="35">
</dataflow>
<dataflow id="210" from="zext_ln394" to="sample_1_addr" fromId="33" toId="35">
</dataflow>
<dataflow id="211" from="sample_2" to="sample_2_addr" fromId="13" toId="36">
</dataflow>
<dataflow id="212" from="StgValue_205" to="sample_2_addr" fromId="205" toId="36">
</dataflow>
<dataflow id="213" from="zext_ln394" to="sample_2_addr" fromId="33" toId="36">
</dataflow>
<dataflow id="214" from="sample_3" to="sample_3_addr" fromId="14" toId="37">
</dataflow>
<dataflow id="215" from="StgValue_205" to="sample_3_addr" fromId="205" toId="37">
</dataflow>
<dataflow id="216" from="zext_ln394" to="sample_3_addr" fromId="33" toId="37">
</dataflow>
<dataflow id="217" from="sample_4" to="sample_4_addr" fromId="15" toId="38">
</dataflow>
<dataflow id="218" from="StgValue_205" to="sample_4_addr" fromId="205" toId="38">
</dataflow>
<dataflow id="219" from="zext_ln394" to="sample_4_addr" fromId="33" toId="38">
</dataflow>
<dataflow id="220" from="sample_5" to="sample_5_addr" fromId="16" toId="39">
</dataflow>
<dataflow id="221" from="StgValue_205" to="sample_5_addr" fromId="205" toId="39">
</dataflow>
<dataflow id="222" from="zext_ln394" to="sample_5_addr" fromId="33" toId="39">
</dataflow>
<dataflow id="223" from="sample_6" to="sample_6_addr" fromId="17" toId="40">
</dataflow>
<dataflow id="224" from="StgValue_205" to="sample_6_addr" fromId="205" toId="40">
</dataflow>
<dataflow id="225" from="zext_ln394" to="sample_6_addr" fromId="33" toId="40">
</dataflow>
<dataflow id="226" from="sample_7" to="sample_7_addr" fromId="18" toId="41">
</dataflow>
<dataflow id="227" from="StgValue_205" to="sample_7_addr" fromId="205" toId="41">
</dataflow>
<dataflow id="228" from="zext_ln394" to="sample_7_addr" fromId="33" toId="41">
</dataflow>
<dataflow id="229" from="trunc_ln394" to="switch_ln394" fromId="31" toId="42">
</dataflow>
<dataflow id="231" from="StgValue_230" to="switch_ln394" fromId="230" toId="42">
</dataflow>
<dataflow id="233" from="StgValue_232" to="switch_ln394" fromId="232" toId="42">
</dataflow>
<dataflow id="235" from="StgValue_234" to="switch_ln394" fromId="234" toId="42">
</dataflow>
<dataflow id="237" from="StgValue_236" to="switch_ln394" fromId="236" toId="42">
</dataflow>
<dataflow id="239" from="StgValue_238" to="switch_ln394" fromId="238" toId="42">
</dataflow>
<dataflow id="241" from="StgValue_240" to="switch_ln394" fromId="240" toId="42">
</dataflow>
<dataflow id="243" from="StgValue_242" to="switch_ln394" fromId="242" toId="42">
</dataflow>
<dataflow id="244" from="tmp" to="store_ln394" fromId="30" toId="43">
</dataflow>
<dataflow id="245" from="sample_6_addr" to="store_ln394" fromId="40" toId="43">
</dataflow>
<dataflow id="246" from="tmp" to="store_ln394" fromId="30" toId="45">
</dataflow>
<dataflow id="247" from="sample_5_addr" to="store_ln394" fromId="39" toId="45">
</dataflow>
<dataflow id="248" from="tmp" to="store_ln394" fromId="30" toId="47">
</dataflow>
<dataflow id="249" from="sample_4_addr" to="store_ln394" fromId="38" toId="47">
</dataflow>
<dataflow id="250" from="tmp" to="store_ln394" fromId="30" toId="49">
</dataflow>
<dataflow id="251" from="sample_3_addr" to="store_ln394" fromId="37" toId="49">
</dataflow>
<dataflow id="252" from="tmp" to="store_ln394" fromId="30" toId="51">
</dataflow>
<dataflow id="253" from="sample_2_addr" to="store_ln394" fromId="36" toId="51">
</dataflow>
<dataflow id="254" from="tmp" to="store_ln394" fromId="30" toId="53">
</dataflow>
<dataflow id="255" from="sample_1_addr" to="store_ln394" fromId="35" toId="53">
</dataflow>
<dataflow id="256" from="tmp" to="store_ln394" fromId="30" toId="55">
</dataflow>
<dataflow id="257" from="sample_0_addr" to="store_ln394" fromId="34" toId="55">
</dataflow>
<dataflow id="258" from="tmp" to="store_ln394" fromId="30" toId="57">
</dataflow>
<dataflow id="259" from="sample_7_addr" to="store_ln394" fromId="41" toId="57">
</dataflow>
<dataflow id="261" from="mlp_kernel" to="call_ln398" fromId="260" toId="59">
</dataflow>
<dataflow id="262" from="sample_0" to="call_ln398" fromId="11" toId="59">
</dataflow>
<dataflow id="263" from="sample_1" to="call_ln398" fromId="12" toId="59">
</dataflow>
<dataflow id="264" from="sample_2" to="call_ln398" fromId="13" toId="59">
</dataflow>
<dataflow id="265" from="sample_3" to="call_ln398" fromId="14" toId="59">
</dataflow>
<dataflow id="266" from="sample_4" to="call_ln398" fromId="15" toId="59">
</dataflow>
<dataflow id="267" from="sample_5" to="call_ln398" fromId="16" toId="59">
</dataflow>
<dataflow id="268" from="sample_6" to="call_ln398" fromId="17" toId="59">
</dataflow>
<dataflow id="269" from="sample_7" to="call_ln398" fromId="18" toId="59">
</dataflow>
<dataflow id="270" from="prediction_0" to="call_ln398" fromId="19" toId="59">
</dataflow>
<dataflow id="271" from="prediction_1" to="call_ln398" fromId="20" toId="59">
</dataflow>
<dataflow id="272" from="l1_weights_1" to="call_ln398" fromId="102" toId="59">
</dataflow>
<dataflow id="273" from="l1_weights_0" to="call_ln398" fromId="103" toId="59">
</dataflow>
<dataflow id="274" from="l1_biases_1" to="call_ln398" fromId="104" toId="59">
</dataflow>
<dataflow id="275" from="l1_biases_0" to="call_ln398" fromId="105" toId="59">
</dataflow>
<dataflow id="276" from="l2_weights_1" to="call_ln398" fromId="106" toId="59">
</dataflow>
<dataflow id="277" from="l2_weights_0" to="call_ln398" fromId="107" toId="59">
</dataflow>
<dataflow id="278" from="l2_biases_1" to="call_ln398" fromId="108" toId="59">
</dataflow>
<dataflow id="279" from="l2_biases_0" to="call_ln398" fromId="109" toId="59">
</dataflow>
<dataflow id="280" from="mlp_kernel" to="call_ln398" fromId="260" toId="61">
</dataflow>
<dataflow id="281" from="sample_0" to="call_ln398" fromId="11" toId="61">
</dataflow>
<dataflow id="282" from="sample_1" to="call_ln398" fromId="12" toId="61">
</dataflow>
<dataflow id="283" from="sample_2" to="call_ln398" fromId="13" toId="61">
</dataflow>
<dataflow id="284" from="sample_3" to="call_ln398" fromId="14" toId="61">
</dataflow>
<dataflow id="285" from="sample_4" to="call_ln398" fromId="15" toId="61">
</dataflow>
<dataflow id="286" from="sample_5" to="call_ln398" fromId="16" toId="61">
</dataflow>
<dataflow id="287" from="sample_6" to="call_ln398" fromId="17" toId="61">
</dataflow>
<dataflow id="288" from="sample_7" to="call_ln398" fromId="18" toId="61">
</dataflow>
<dataflow id="289" from="prediction_0" to="call_ln398" fromId="19" toId="61">
</dataflow>
<dataflow id="290" from="prediction_1" to="call_ln398" fromId="20" toId="61">
</dataflow>
<dataflow id="291" from="l1_weights_1" to="call_ln398" fromId="102" toId="61">
</dataflow>
<dataflow id="292" from="l1_weights_0" to="call_ln398" fromId="103" toId="61">
</dataflow>
<dataflow id="293" from="l1_biases_1" to="call_ln398" fromId="104" toId="61">
</dataflow>
<dataflow id="294" from="l1_biases_0" to="call_ln398" fromId="105" toId="61">
</dataflow>
<dataflow id="295" from="l2_weights_1" to="call_ln398" fromId="106" toId="61">
</dataflow>
<dataflow id="296" from="l2_weights_0" to="call_ln398" fromId="107" toId="61">
</dataflow>
<dataflow id="297" from="l2_biases_1" to="call_ln398" fromId="108" toId="61">
</dataflow>
<dataflow id="298" from="l2_biases_0" to="call_ln398" fromId="109" toId="61">
</dataflow>
<dataflow id="300" from="StgValue_299" to="i1_0" fromId="299" toId="63">
<condition id="-1">
<or_exp><and_exp></and_exp></or_exp>
</condition>
</dataflow>
<dataflow id="301" from="br_ln401" to="i1_0" fromId="62" toId="63">
</dataflow>
<dataflow id="302" from="i" to="i1_0" fromId="66" toId="63">
<BackEdge/>
<condition id="-1">
<or_exp><and_exp></and_exp></or_exp>
</condition>
</dataflow>
<dataflow id="303" from="br_ln401" to="i1_0" fromId="82" toId="63">
<BackEdge/>
</dataflow>
<dataflow id="304" from="i1_0" to="icmp_ln401" fromId="63" toId="64">
</dataflow>
<dataflow id="306" from="StgValue_305" to="icmp_ln401" fromId="305" toId="64">
</dataflow>
<dataflow id="307" from="_ssdm_op_SpecLoopTripCount" to="empty_16" fromId="178" toId="65">
</dataflow>
<dataflow id="309" from="StgValue_308" to="empty_16" fromId="308" toId="65">
</dataflow>
<dataflow id="310" from="StgValue_308" to="empty_16" fromId="308" toId="65">
</dataflow>
<dataflow id="311" from="StgValue_308" to="empty_16" fromId="308" toId="65">
</dataflow>
<dataflow id="312" from="i1_0" to="i" fromId="63" toId="66">
</dataflow>
<dataflow id="314" from="StgValue_313" to="i" fromId="313" toId="66">
</dataflow>
<dataflow id="315" from="icmp_ln401" to="br_ln401" fromId="64" toId="67">
</dataflow>
<dataflow id="316" from="i1_0" to="trunc_ln403" fromId="63" toId="68">
</dataflow>
<dataflow id="318" from="_ssdm_op_PartSelect.i3.i4.i32.i32" to="lshr_ln4" fromId="317" toId="69">
</dataflow>
<dataflow id="319" from="i1_0" to="lshr_ln4" fromId="63" toId="69">
</dataflow>
<dataflow id="320" from="StgValue_135" to="lshr_ln4" fromId="135" toId="69">
</dataflow>
<dataflow id="321" from="StgValue_199" to="lshr_ln4" fromId="199" toId="69">
</dataflow>
<dataflow id="322" from="lshr_ln4" to="zext_ln403" fromId="69" toId="70">
</dataflow>
<dataflow id="323" from="prediction_0" to="prediction_0_addr" fromId="19" toId="71">
</dataflow>
<dataflow id="324" from="StgValue_205" to="prediction_0_addr" fromId="205" toId="71">
</dataflow>
<dataflow id="325" from="zext_ln403" to="prediction_0_addr" fromId="70" toId="71">
</dataflow>
<dataflow id="326" from="prediction_1" to="prediction_1_addr" fromId="20" toId="72">
</dataflow>
<dataflow id="327" from="StgValue_205" to="prediction_1_addr" fromId="205" toId="72">
</dataflow>
<dataflow id="328" from="zext_ln403" to="prediction_1_addr" fromId="70" toId="72">
</dataflow>
<dataflow id="329" from="prediction_1_addr" to="prediction_1_load" fromId="72" toId="73">
</dataflow>
<dataflow id="330" from="prediction_0_addr" to="prediction_0_load" fromId="71" toId="74">
</dataflow>
<dataflow id="331" from="prediction_1_addr" to="prediction_1_load" fromId="72" toId="76">
</dataflow>
<dataflow id="332" from="prediction_0_addr" to="prediction_0_load" fromId="71" toId="77">
</dataflow>
<dataflow id="333" from="trunc_ln403" to="tmp_4" fromId="68" toId="78">
</dataflow>
<dataflow id="334" from="prediction_1_load" to="tmp_4" fromId="76" toId="78">
</dataflow>
<dataflow id="335" from="prediction_0_load" to="tmp_4" fromId="77" toId="78">
</dataflow>
<dataflow id="337" from="_ssdm_op_Write.axis.volatile.i16P" to="write_ln403" fromId="336" toId="79">
</dataflow>
<dataflow id="338" from="out_V" to="write_ln403" fromId="101" toId="79">
</dataflow>
<dataflow id="339" from="tmp_4" to="write_ln403" fromId="78" toId="79">
</dataflow>
<dataflow id="340" from="_ssdm_op_SpecLoopName" to="specloopname_ln402" fromId="188" toId="80">
</dataflow>
<dataflow id="342" from="p_str8" to="specloopname_ln402" fromId="341" toId="80">
</dataflow>
<dataflow id="343" from="_ssdm_op_Write.axis.volatile.i16P" to="write_ln403" fromId="336" toId="81">
</dataflow>
<dataflow id="344" from="out_V" to="write_ln403" fromId="101" toId="81">
</dataflow>
<dataflow id="345" from="tmp_4" to="write_ln403" fromId="78" toId="81">
</dataflow>
<dataflow id="346" from="icmp_ln392" to="StgValue_2" fromId="25" toId="2">
</dataflow>
<dataflow id="347" from="trunc_ln394" to="StgValue_2" fromId="31" toId="2">
</dataflow>
<dataflow id="348" from="icmp_ln401" to="StgValue_5" fromId="64" toId="5">
</dataflow>
</dataflows>


</stg>
