<?xml version="1.0" encoding="UTF-8"?>
<vivadoHLSLog:LogRoot xmlns:vivadoHLSLog="www.xilinx.com/vivadoHLSLog">
  <errorLogs>
    <logs>
      <synLog/>
      <simLog/>
      <mgLog/>
      <packageLog/>
      <csimLog/>
    </logs>
  </errorLogs>
  <warningLogs>
    <logs>
      <synLog>
        <logs message="WARNING: [RTMG 210-274] Memory 'mlp_kernel_l3_weibil' is read-only, switch it to a ROM." projectName="hls" solutionName="solution1" date="2024-02-03T18:09:00.555+0100" type="Warning"/>
        <logs message="WARNING: [RTMG 210-274] Memory 'mlp_kernel_l3_weibhl' is read-only, switch it to a ROM." projectName="hls" solutionName="solution1" date="2024-02-03T18:09:00.525+0100" type="Warning"/>
        <logs message="WARNING: [RTMG 210-274] Memory 'mlp_kernel_l3_weibgk' is read-only, switch it to a ROM." projectName="hls" solutionName="solution1" date="2024-02-03T18:09:00.450+0100" type="Warning"/>
        <logs message="WARNING: [RTMG 210-274] Memory 'mlp_kernel_l3_weibfk' is read-only, switch it to a ROM." projectName="hls" solutionName="solution1" date="2024-02-03T18:09:00.421+0100" type="Warning"/>
        <logs message="WARNING: [RTMG 210-274] Memory 'mlp_kernel_l3_weibek' is read-only, switch it to a ROM." projectName="hls" solutionName="solution1" date="2024-02-03T18:09:00.364+0100" type="Warning"/>
        <logs message="WARNING: [RTMG 210-274] Memory 'mlp_kernel_l3_weibdk' is read-only, switch it to a ROM." projectName="hls" solutionName="solution1" date="2024-02-03T18:09:00.335+0100" type="Warning"/>
        <logs message="WARNING: [RTMG 210-274] Memory 'mlp_kernel_l3_weibck' is read-only, switch it to a ROM." projectName="hls" solutionName="solution1" date="2024-02-03T18:09:00.308+0100" type="Warning"/>
        <logs message="WARNING: [RTMG 210-274] Memory 'mlp_kernel_l3_weibbk' is read-only, switch it to a ROM." projectName="hls" solutionName="solution1" date="2024-02-03T18:09:00.242+0100" type="Warning"/>
        <logs message="WARNING: [RTMG 210-274] Memory 'mlp_kernel_l3_weibak' is read-only, switch it to a ROM." projectName="hls" solutionName="solution1" date="2024-02-03T18:09:00.208+0100" type="Warning"/>
        <logs message="WARNING: [RTMG 210-274] Memory 'mlp_kernel_l3_wei9j0' is read-only, switch it to a ROM." projectName="hls" solutionName="solution1" date="2024-02-03T18:09:00.119+0100" type="Warning"/>
        <logs message="WARNING: [RTMG 210-274] Memory 'mlp_kernel_l2_weiKfY' is read-only, switch it to a ROM." projectName="hls" solutionName="solution1" date="2024-02-03T18:08:59.783+0100" type="Warning"/>
        <logs message="WARNING: [RTMG 210-274] Memory 'mlp_kernel_l2_weiJfO' is read-only, switch it to a ROM." projectName="hls" solutionName="solution1" date="2024-02-03T18:08:59.721+0100" type="Warning"/>
        <logs message="WARNING: [RTMG 210-274] Memory 'mlp_kernel_l2_weiIfE' is read-only, switch it to a ROM." projectName="hls" solutionName="solution1" date="2024-02-03T18:08:59.613+0100" type="Warning"/>
        <logs message="WARNING: [RTMG 210-274] Memory 'mlp_kernel_l2_weiHfu' is read-only, switch it to a ROM." projectName="hls" solutionName="solution1" date="2024-02-03T18:08:59.535+0100" type="Warning"/>
        <logs message="WARNING: [RTMG 210-274] Memory 'mlp_kernel_l2_weiGfk' is read-only, switch it to a ROM." projectName="hls" solutionName="solution1" date="2024-02-03T18:08:59.496+0100" type="Warning"/>
        <logs message="WARNING: [RTMG 210-274] Memory 'mlp_kernel_l2_weiFfa' is read-only, switch it to a ROM." projectName="hls" solutionName="solution1" date="2024-02-03T18:08:59.463+0100" type="Warning"/>
        <logs message="WARNING: [RTMG 210-274] Memory 'mlp_kernel_l2_weiEe0' is read-only, switch it to a ROM." projectName="hls" solutionName="solution1" date="2024-02-03T18:08:59.406+0100" type="Warning"/>
        <logs message="WARNING: [RTMG 210-274] Memory 'mlp_kernel_l2_weiDeQ' is read-only, switch it to a ROM." projectName="hls" solutionName="solution1" date="2024-02-03T18:08:59.373+0100" type="Warning"/>
        <logs message="WARNING: [RTMG 210-274] Memory 'mlp_kernel_l2_weiCeG' is read-only, switch it to a ROM." projectName="hls" solutionName="solution1" date="2024-02-03T18:08:59.312+0100" type="Warning"/>
        <logs message="WARNING: [RTMG 210-274] Memory 'mlp_kernel_l2_weiBew' is read-only, switch it to a ROM." projectName="hls" solutionName="solution1" date="2024-02-03T18:08:59.273+0100" type="Warning"/>
        <logs message="WARNING: [RTMG 210-274] Memory 'mlp_kernel_l2_weiAem' is read-only, switch it to a ROM." projectName="hls" solutionName="solution1" date="2024-02-03T18:08:59.202+0100" type="Warning"/>
        <logs message="WARNING: [RTMG 210-274] Memory 'mlp_kernel_l2_weizec' is read-only, switch it to a ROM." projectName="hls" solutionName="solution1" date="2024-02-03T18:08:59.122+0100" type="Warning"/>
        <logs message="WARNING: [RTMG 210-274] Memory 'mlp_kernel_l2_weiyd2' is read-only, switch it to a ROM." projectName="hls" solutionName="solution1" date="2024-02-03T18:08:59.079+0100" type="Warning"/>
        <logs message="WARNING: [RTMG 210-274] Memory 'mlp_kernel_l2_weixdS' is read-only, switch it to a ROM." projectName="hls" solutionName="solution1" date="2024-02-03T18:08:59.004+0100" type="Warning"/>
        <logs message="WARNING: [RTMG 210-274] Memory 'mlp_kernel_l2_weiwdI' is read-only, switch it to a ROM." projectName="hls" solutionName="solution1" date="2024-02-03T18:08:58.925+0100" type="Warning"/>
        <logs message="WARNING: [RTMG 210-274] Memory 'mlp_kernel_l2_weivdy' is read-only, switch it to a ROM." projectName="hls" solutionName="solution1" date="2024-02-03T18:08:58.850+0100" type="Warning"/>
        <logs message="WARNING: [RTMG 210-274] Memory 'mlp_kernel_l2_weiudo' is read-only, switch it to a ROM." projectName="hls" solutionName="solution1" date="2024-02-03T18:08:58.787+0100" type="Warning"/>
        <logs message="WARNING: [RTMG 210-274] Memory 'mlp_kernel_l2_weitde' is read-only, switch it to a ROM." projectName="hls" solutionName="solution1" date="2024-02-03T18:08:58.712+0100" type="Warning"/>
        <logs message="WARNING: [RTMG 210-274] Memory 'mlp_kernel_l2_weisc4' is read-only, switch it to a ROM." projectName="hls" solutionName="solution1" date="2024-02-03T18:08:58.649+0100" type="Warning"/>
        <logs message="WARNING: [RTMG 210-274] Memory 'mlp_kernel_l2_weircU' is read-only, switch it to a ROM." projectName="hls" solutionName="solution1" date="2024-02-03T18:08:58.616+0100" type="Warning"/>
        <logs message="WARNING: [RTMG 210-274] Memory 'mlp_kernel_l2_weiqcK' is read-only, switch it to a ROM." projectName="hls" solutionName="solution1" date="2024-02-03T18:08:58.549+0100" type="Warning"/>
        <logs message="WARNING: [RTMG 210-274] Memory 'mlp_kernel_l2_weipcA' is read-only, switch it to a ROM." projectName="hls" solutionName="solution1" date="2024-02-03T18:08:58.517+0100" type="Warning"/>
        <logs message="WARNING: [RTMG 210-274] Memory 'mlp_kernel_l2_weiocq' is read-only, switch it to a ROM." projectName="hls" solutionName="solution1" date="2024-02-03T18:08:58.414+0100" type="Warning"/>
        <logs message="WARNING: [RTMG 210-274] Memory 'mlp_kernel_l2_weincg' is read-only, switch it to a ROM." projectName="hls" solutionName="solution1" date="2024-02-03T18:08:58.339+0100" type="Warning"/>
        <logs message="WARNING: [RTMG 210-274] Memory 'mlp_kernel_l2_weimb6' is read-only, switch it to a ROM." projectName="hls" solutionName="solution1" date="2024-02-03T18:08:58.303+0100" type="Warning"/>
        <logs message="WARNING: [RTMG 210-274] Memory 'mlp_kernel_l2_weilbW' is read-only, switch it to a ROM." projectName="hls" solutionName="solution1" date="2024-02-03T18:08:58.237+0100" type="Warning"/>
        <logs message="WARNING: [RTMG 210-274] Memory 'mlp_kernel_l2_weikbM' is read-only, switch it to a ROM." projectName="hls" solutionName="solution1" date="2024-02-03T18:08:58.206+0100" type="Warning"/>
        <logs message="WARNING: [RTMG 210-274] Memory 'mlp_kernel_l2_weijbC' is read-only, switch it to a ROM." projectName="hls" solutionName="solution1" date="2024-02-03T18:08:58.177+0100" type="Warning"/>
        <logs message="WARNING: [RTMG 210-274] Memory 'mlp_kernel_l2_weiibs' is read-only, switch it to a ROM." projectName="hls" solutionName="solution1" date="2024-02-03T18:08:58.121+0100" type="Warning"/>
        <logs message="WARNING: [RTMG 210-274] Memory 'mlp_kernel_l2_weihbi' is read-only, switch it to a ROM." projectName="hls" solutionName="solution1" date="2024-02-03T18:08:58.092+0100" type="Warning"/>
        <logs message="WARNING: [RTMG 210-274] Memory 'mlp_kernel_l2_weig8j' is read-only, switch it to a ROM." projectName="hls" solutionName="solution1" date="2024-02-03T18:08:58.057+0100" type="Warning"/>
        <logs message="WARNING: [RTMG 210-274] Memory 'mlp_kernel_l2_weifYi' is read-only, switch it to a ROM." projectName="hls" solutionName="solution1" date="2024-02-03T18:08:57.997+0100" type="Warning"/>
        <logs message="WARNING: [RTMG 210-274] Memory 'mlp_kernel_l1_weieOg' is read-only, switch it to a ROM." projectName="hls" solutionName="solution1" date="2024-02-03T18:08:57.943+0100" type="Warning"/>
        <logs message="WARNING: [RTMG 210-274] Memory 'mlp_kernel_l1_weidEe' is read-only, switch it to a ROM." projectName="hls" solutionName="solution1" date="2024-02-03T18:08:57.841+0100" type="Warning"/>
        <logs message="WARNING: [RTMG 210-274] Memory 'mlp_kernel_l1_weicud' is read-only, switch it to a ROM." projectName="hls" solutionName="solution1" date="2024-02-03T18:08:57.752+0100" type="Warning"/>
        <logs message="WARNING: [RTGEN 206-101] Global array 'mlp_kernel_unsigned_s' will not be exposed as RTL port." projectName="hls" solutionName="solution1" date="2024-02-03T18:08:49.560+0100" type="Warning"/>
        <logs message="WARNING: [SCHED 204-69] Unable to schedule 'store' operation ('sample_addr_2_write_ln149', mnist_mlp.cpp:149) of variable 'p_Result_s', mnist_mlp.cpp:149 on array 'sample', mnist_mlp.cpp:128 due to limited memory ports. Please consider using a memory core with more ports or partitioning the array 'sample'." projectName="hls" solutionName="solution1" date="2024-02-03T18:08:29.927+0100" type="Warning"/>
        <logs message="WARNING: [BIND 205-102] The specified resource core for memory 'l1_weights_63' will be ignored if a simpler one can be used." projectName="hls" solutionName="solution1" date="2024-02-03T18:08:21.419+0100" type="Warning"/>
        <logs message="WARNING: [BIND 205-102] The specified resource core for memory 'l1_weights_62' will be ignored if a simpler one can be used." projectName="hls" solutionName="solution1" date="2024-02-03T18:08:21.353+0100" type="Warning"/>
        <logs message="WARNING: [BIND 205-102] The specified resource core for memory 'l1_weights_61' will be ignored if a simpler one can be used." projectName="hls" solutionName="solution1" date="2024-02-03T18:08:21.347+0100" type="Warning"/>
        <logs message="WARNING: [BIND 205-102] The specified resource core for memory 'l1_weights_60' will be ignored if a simpler one can be used." projectName="hls" solutionName="solution1" date="2024-02-03T18:08:21.330+0100" type="Warning"/>
        <logs message="WARNING: [BIND 205-102] The specified resource core for memory 'l1_weights_59' will be ignored if a simpler one can be used." projectName="hls" solutionName="solution1" date="2024-02-03T18:08:21.317+0100" type="Warning"/>
        <logs message="WARNING: [BIND 205-102] The specified resource core for memory 'l1_weights_58' will be ignored if a simpler one can be used." projectName="hls" solutionName="solution1" date="2024-02-03T18:08:21.305+0100" type="Warning"/>
        <logs message="WARNING: [BIND 205-102] The specified resource core for memory 'l1_weights_57' will be ignored if a simpler one can be used." projectName="hls" solutionName="solution1" date="2024-02-03T18:08:21.291+0100" type="Warning"/>
        <logs message="WARNING: [BIND 205-102] The specified resource core for memory 'l1_weights_56' will be ignored if a simpler one can be used." projectName="hls" solutionName="solution1" date="2024-02-03T18:08:21.284+0100" type="Warning"/>
        <logs message="WARNING: [BIND 205-102] The specified resource core for memory 'l1_weights_55' will be ignored if a simpler one can be used." projectName="hls" solutionName="solution1" date="2024-02-03T18:08:21.260+0100" type="Warning"/>
        <logs message="WARNING: [BIND 205-102] The specified resource core for memory 'l1_weights_54' will be ignored if a simpler one can be used." projectName="hls" solutionName="solution1" date="2024-02-03T18:08:21.255+0100" type="Warning"/>
        <logs message="WARNING: [BIND 205-102] The specified resource core for memory 'l1_weights_53' will be ignored if a simpler one can be used." projectName="hls" solutionName="solution1" date="2024-02-03T18:08:21.249+0100" type="Warning"/>
        <logs message="WARNING: [BIND 205-102] The specified resource core for memory 'l1_weights_52' will be ignored if a simpler one can be used." projectName="hls" solutionName="solution1" date="2024-02-03T18:08:21.242+0100" type="Warning"/>
        <logs message="WARNING: [BIND 205-102] The specified resource core for memory 'l1_weights_51' will be ignored if a simpler one can be used." projectName="hls" solutionName="solution1" date="2024-02-03T18:08:21.237+0100" type="Warning"/>
        <logs message="WARNING: [BIND 205-102] The specified resource core for memory 'l1_weights_50' will be ignored if a simpler one can be used." projectName="hls" solutionName="solution1" date="2024-02-03T18:08:21.231+0100" type="Warning"/>
        <logs message="WARNING: [BIND 205-102] The specified resource core for memory 'l1_weights_49' will be ignored if a simpler one can be used." projectName="hls" solutionName="solution1" date="2024-02-03T18:08:21.226+0100" type="Warning"/>
        <logs message="WARNING: [BIND 205-102] The specified resource core for memory 'l1_weights_48' will be ignored if a simpler one can be used." projectName="hls" solutionName="solution1" date="2024-02-03T18:08:21.221+0100" type="Warning"/>
        <logs message="WARNING: [BIND 205-102] The specified resource core for memory 'l1_weights_47' will be ignored if a simpler one can be used." projectName="hls" solutionName="solution1" date="2024-02-03T18:08:21.214+0100" type="Warning"/>
        <logs message="WARNING: [BIND 205-102] The specified resource core for memory 'l1_weights_46' will be ignored if a simpler one can be used." projectName="hls" solutionName="solution1" date="2024-02-03T18:08:21.207+0100" type="Warning"/>
        <logs message="WARNING: [BIND 205-102] The specified resource core for memory 'l1_weights_45' will be ignored if a simpler one can be used." projectName="hls" solutionName="solution1" date="2024-02-03T18:08:21.202+0100" type="Warning"/>
        <logs message="WARNING: [BIND 205-102] The specified resource core for memory 'l1_weights_44' will be ignored if a simpler one can be used." projectName="hls" solutionName="solution1" date="2024-02-03T18:08:21.195+0100" type="Warning"/>
        <logs message="WARNING: [BIND 205-102] The specified resource core for memory 'l1_weights_43' will be ignored if a simpler one can be used." projectName="hls" solutionName="solution1" date="2024-02-03T18:08:21.190+0100" type="Warning"/>
        <logs message="WARNING: [BIND 205-102] The specified resource core for memory 'l1_weights_42' will be ignored if a simpler one can be used." projectName="hls" solutionName="solution1" date="2024-02-03T18:08:21.185+0100" type="Warning"/>
        <logs message="WARNING: [BIND 205-102] The specified resource core for memory 'l1_weights_41' will be ignored if a simpler one can be used." projectName="hls" solutionName="solution1" date="2024-02-03T18:08:21.180+0100" type="Warning"/>
        <logs message="WARNING: [BIND 205-102] The specified resource core for memory 'l1_weights_40' will be ignored if a simpler one can be used." projectName="hls" solutionName="solution1" date="2024-02-03T18:08:21.174+0100" type="Warning"/>
        <logs message="WARNING: [BIND 205-102] The specified resource core for memory 'l1_weights_39' will be ignored if a simpler one can be used." projectName="hls" solutionName="solution1" date="2024-02-03T18:08:21.166+0100" type="Warning"/>
        <logs message="WARNING: [BIND 205-102] The specified resource core for memory 'l1_weights_38' will be ignored if a simpler one can be used." projectName="hls" solutionName="solution1" date="2024-02-03T18:08:21.161+0100" type="Warning"/>
        <logs message="WARNING: [BIND 205-102] The specified resource core for memory 'l1_weights_37' will be ignored if a simpler one can be used." projectName="hls" solutionName="solution1" date="2024-02-03T18:08:21.152+0100" type="Warning"/>
        <logs message="WARNING: [BIND 205-102] The specified resource core for memory 'l1_weights_36' will be ignored if a simpler one can be used." projectName="hls" solutionName="solution1" date="2024-02-03T18:08:21.147+0100" type="Warning"/>
        <logs message="WARNING: [BIND 205-102] The specified resource core for memory 'l1_weights_35' will be ignored if a simpler one can be used." projectName="hls" solutionName="solution1" date="2024-02-03T18:08:21.136+0100" type="Warning"/>
        <logs message="WARNING: [BIND 205-102] The specified resource core for memory 'l1_weights_34' will be ignored if a simpler one can be used." projectName="hls" solutionName="solution1" date="2024-02-03T18:08:21.119+0100" type="Warning"/>
        <logs message="WARNING: [BIND 205-102] The specified resource core for memory 'l1_weights_33' will be ignored if a simpler one can be used." projectName="hls" solutionName="solution1" date="2024-02-03T18:08:21.111+0100" type="Warning"/>
        <logs message="WARNING: [BIND 205-102] The specified resource core for memory 'l1_weights_32' will be ignored if a simpler one can be used." projectName="hls" solutionName="solution1" date="2024-02-03T18:08:21.100+0100" type="Warning"/>
        <logs message="WARNING: [BIND 205-102] The specified resource core for memory 'l1_weights_31' will be ignored if a simpler one can be used." projectName="hls" solutionName="solution1" date="2024-02-03T18:08:21.084+0100" type="Warning"/>
        <logs message="WARNING: [BIND 205-102] The specified resource core for memory 'l1_weights_30' will be ignored if a simpler one can be used." projectName="hls" solutionName="solution1" date="2024-02-03T18:08:21.078+0100" type="Warning"/>
        <logs message="WARNING: [BIND 205-102] The specified resource core for memory 'l1_weights_29' will be ignored if a simpler one can be used." projectName="hls" solutionName="solution1" date="2024-02-03T18:08:21.039+0100" type="Warning"/>
        <logs message="WARNING: [BIND 205-102] The specified resource core for memory 'l1_weights_28' will be ignored if a simpler one can be used." projectName="hls" solutionName="solution1" date="2024-02-03T18:08:21.027+0100" type="Warning"/>
        <logs message="WARNING: [BIND 205-102] The specified resource core for memory 'l1_weights_27' will be ignored if a simpler one can be used." projectName="hls" solutionName="solution1" date="2024-02-03T18:08:21.018+0100" type="Warning"/>
        <logs message="WARNING: [BIND 205-102] The specified resource core for memory 'l1_weights_26' will be ignored if a simpler one can be used." projectName="hls" solutionName="solution1" date="2024-02-03T18:08:21.004+0100" type="Warning"/>
        <logs message="WARNING: [BIND 205-102] The specified resource core for memory 'l1_weights_25' will be ignored if a simpler one can be used." projectName="hls" solutionName="solution1" date="2024-02-03T18:08:20.994+0100" type="Warning"/>
        <logs message="WARNING: [BIND 205-102] The specified resource core for memory 'l1_weights_24' will be ignored if a simpler one can be used." projectName="hls" solutionName="solution1" date="2024-02-03T18:08:20.980+0100" type="Warning"/>
        <logs message="WARNING: [BIND 205-102] The specified resource core for memory 'l1_weights_23' will be ignored if a simpler one can be used." projectName="hls" solutionName="solution1" date="2024-02-03T18:08:20.973+0100" type="Warning"/>
        <logs message="WARNING: [BIND 205-102] The specified resource core for memory 'l1_weights_22' will be ignored if a simpler one can be used." projectName="hls" solutionName="solution1" date="2024-02-03T18:08:20.965+0100" type="Warning"/>
        <logs message="WARNING: [BIND 205-102] The specified resource core for memory 'l1_weights_21' will be ignored if a simpler one can be used." projectName="hls" solutionName="solution1" date="2024-02-03T18:08:20.949+0100" type="Warning"/>
        <logs message="WARNING: [BIND 205-102] The specified resource core for memory 'l1_weights_20' will be ignored if a simpler one can be used." projectName="hls" solutionName="solution1" date="2024-02-03T18:08:20.936+0100" type="Warning"/>
        <logs message="WARNING: [BIND 205-102] The specified resource core for memory 'l1_weights_19' will be ignored if a simpler one can be used." projectName="hls" solutionName="solution1" date="2024-02-03T18:08:20.923+0100" type="Warning"/>
        <logs message="WARNING: [BIND 205-102] The specified resource core for memory 'l1_weights_18' will be ignored if a simpler one can be used." projectName="hls" solutionName="solution1" date="2024-02-03T18:08:20.912+0100" type="Warning"/>
        <logs message="WARNING: [BIND 205-102] The specified resource core for memory 'l1_weights_17' will be ignored if a simpler one can be used." projectName="hls" solutionName="solution1" date="2024-02-03T18:08:20.898+0100" type="Warning"/>
        <logs message="WARNING: [BIND 205-102] The specified resource core for memory 'l1_weights_16' will be ignored if a simpler one can be used." projectName="hls" solutionName="solution1" date="2024-02-03T18:08:20.884+0100" type="Warning"/>
        <logs message="WARNING: [BIND 205-102] The specified resource core for memory 'l1_weights_15' will be ignored if a simpler one can be used." projectName="hls" solutionName="solution1" date="2024-02-03T18:08:20.870+0100" type="Warning"/>
        <logs message="WARNING: [BIND 205-102] The specified resource core for memory 'l1_weights_14' will be ignored if a simpler one can be used." projectName="hls" solutionName="solution1" date="2024-02-03T18:08:20.861+0100" type="Warning"/>
        <logs message="WARNING: [BIND 205-102] The specified resource core for memory 'l1_weights_13' will be ignored if a simpler one can be used." projectName="hls" solutionName="solution1" date="2024-02-03T18:08:20.845+0100" type="Warning"/>
        <logs message="WARNING: [BIND 205-102] The specified resource core for memory 'l1_weights_12' will be ignored if a simpler one can be used." projectName="hls" solutionName="solution1" date="2024-02-03T18:08:20.829+0100" type="Warning"/>
        <logs message="WARNING: [BIND 205-102] The specified resource core for memory 'l1_weights_11' will be ignored if a simpler one can be used." projectName="hls" solutionName="solution1" date="2024-02-03T18:08:20.818+0100" type="Warning"/>
        <logs message="WARNING: [BIND 205-102] The specified resource core for memory 'l1_weights_10' will be ignored if a simpler one can be used." projectName="hls" solutionName="solution1" date="2024-02-03T18:08:20.803+0100" type="Warning"/>
        <logs message="WARNING: [BIND 205-102] The specified resource core for memory 'l1_weights_9' will be ignored if a simpler one can be used." projectName="hls" solutionName="solution1" date="2024-02-03T18:08:20.788+0100" type="Warning"/>
        <logs message="WARNING: [BIND 205-102] The specified resource core for memory 'l1_weights_8' will be ignored if a simpler one can be used." projectName="hls" solutionName="solution1" date="2024-02-03T18:08:20.777+0100" type="Warning"/>
        <logs message="WARNING: [BIND 205-102] The specified resource core for memory 'l1_weights_7' will be ignored if a simpler one can be used." projectName="hls" solutionName="solution1" date="2024-02-03T18:08:20.763+0100" type="Warning"/>
        <logs message="WARNING: [BIND 205-102] The specified resource core for memory 'l1_weights_6' will be ignored if a simpler one can be used." projectName="hls" solutionName="solution1" date="2024-02-03T18:08:20.745+0100" type="Warning"/>
        <logs message="WARNING: [BIND 205-102] The specified resource core for memory 'l1_weights_5' will be ignored if a simpler one can be used." projectName="hls" solutionName="solution1" date="2024-02-03T18:08:20.735+0100" type="Warning"/>
        <logs message="WARNING: [BIND 205-102] The specified resource core for memory 'l1_weights_4' will be ignored if a simpler one can be used." projectName="hls" solutionName="solution1" date="2024-02-03T18:08:20.713+0100" type="Warning"/>
        <logs message="WARNING: [BIND 205-102] The specified resource core for memory 'l1_weights_3' will be ignored if a simpler one can be used." projectName="hls" solutionName="solution1" date="2024-02-03T18:08:20.691+0100" type="Warning"/>
        <logs message="WARNING: [XFORM 203-105] Cannot partition array 'sample' (mnist_mlp.cpp:128): incorrect partition factor 1." projectName="hls" solutionName="solution1" date="2024-02-03T18:07:57.794+0100" type="Warning"/>
        <logs message="WARNING: [XFORM 203-505] Pipeline directive for loop 'output_bias' (mnist_mlp.cpp:101) in function 'mlp_kernel' has been removed because the loop is unrolled completely." projectName="hls" solutionName="solution1" date="2024-02-03T18:07:56.883+0100" type="Warning"/>
        <logs message="WARNING: [XFORM 203-505] Pipeline directive for loop 'input_bias_relu' (mnist_mlp.cpp:63) in function 'mlp_kernel' has been removed because the loop is unrolled completely." projectName="hls" solutionName="solution1" date="2024-02-03T18:07:56.874+0100" type="Warning"/>
        <logs message="WARNING: [SYNCHK 200-23] mnist_mlp.cpp:149: variable-indexed range selection may cause suboptimal QoR." projectName="hls" solutionName="solution1" date="2024-02-03T18:07:53.576+0100" type="Warning"/>
      </synLog>
      <simLog/>
      <mgLog/>
      <packageLog/>
      <csimLog/>
    </logs>
  </warningLogs>
</vivadoHLSLog:LogRoot>
